json_utils/__init__.py
json_utils/lines.py
json_utils/tree.py
json_utils/utils.py
json_utils/version.py
json_utils_sebastian_achim_mueller-0.0.6.dist-info/licenses/LICENSE
json_utils_sebastian_achim_mueller-0.0.6.dist-info/METADATA
json_utils_sebastian_achim_mueller-0.0.6.dist-info/WHEEL
json_utils_sebastian_achim_mueller-0.0.6.dist-info/top_level.txt
json_utils_sebastian_achim_mueller-0.0.6.dist-info/RECORD
