Metadata-Version: 2.4
Name: json_utils_sebastian-achim-mueller
Version: 0.0.6
Summary: JSON-lines and recursive reading of json-files in a path.
Home-page: https://github.com/cherenkov-plenoscope/json_utils
Author: Sebastian Achim Mueller
Author-email: sebastian-achim.mueller@mpi-hd.mpg.de
Classifier: Natural Language :: English
Classifier: Programming Language :: Python :: 3
Classifier: License :: OSI Approved :: MIT License
Classifier: Operating System :: OS Independent
Requires-Python: >=3.0
License-File: LICENSE
Requires-Dist: json_numpy_sebastian-achim-mueller
Dynamic: author
Dynamic: author-email
Dynamic: classifier
Dynamic: description
Dynamic: description-content-type
Dynamic: home-page
Dynamic: license-file
Dynamic: requires-dist
Dynamic: requires-python
Dynamic: summary
